{"name":"Search for an automation course","id":"academy-choucair;search-for-an-automation-course","testSteps":[{"number":1,"description":"Given than brandon wants to learn automation at the academy choucair\r\n| strUser | strPassword |\r\n| 1128266108 | Choucair2020* |","duration":19199,"startTime":"2020-12-29T14:32:39.787-05:00[America/Bogota]","screenshots":[{"screenshot":"b4edb95ce427180a70791b474e0c4793c1c46fb618adb4a03398baad0bb7b6be.png","timeStamp":1609270378986}],"result":"SUCCESS","precondition":false,"level":0,"lineNumber":0,"children":[{"number":2,"description":"Brandon open up","duration":10029,"startTime":"2020-12-29T14:32:40.755-05:00[America/Bogota]","screenshots":[{"screenshot":"fa1668f49c76263a7b9295edba31973bb5d52dc9222a5ab910cbfa9c55fd8eb0.png","timeStamp":1609270370784}],"result":"SUCCESS","precondition":false,"level":1,"lineNumber":0,"children":[{"number":3,"description":"brandon opens the Choucair academy page","duration":9971,"startTime":"2020-12-29T14:32:40.778-05:00[America/Bogota]","screenshots":[{"screenshot":"fa1668f49c76263a7b9295edba31973bb5d52dc9222a5ab910cbfa9c55fd8eb0.png","timeStamp":1609270370749}],"result":"SUCCESS","precondition":false,"level":2,"lineNumber":0}]},{"number":4,"description":"Brandon login","duration":8184,"startTime":"2020-12-29T14:32:50.784-05:00[America/Bogota]","screenshots":[{"screenshot":"fa1668f49c76263a7b9295edba31973bb5d52dc9222a5ab910cbfa9c55fd8eb0.png","timeStamp":1609270370793},{"screenshot":"b4edb95ce427180a70791b474e0c4793c1c46fb618adb4a03398baad0bb7b6be.png","timeStamp":1609270378968}],"result":"SUCCESS","precondition":false,"level":1,"lineNumber":0,"children":[{"number":5,"description":"brandon clicks on button that shows us the form to login","duration":1720,"startTime":"2020-12-29T14:32:50.860-05:00[America/Bogota]","screenshots":[{"screenshot":"fa1668f49c76263a7b9295edba31973bb5d52dc9222a5ab910cbfa9c55fd8eb0.png","timeStamp":1609270371562},{"screenshot":"014f1f01c62fc569358026ed3b4edd8e30522c31fe52a7c1a519700608f4a605.png","timeStamp":1609270372580}],"result":"SUCCESS","precondition":false,"level":2,"lineNumber":0},{"number":6,"description":"brandon enters \u00271128266108\u0027 into where do we write the user","duration":1064,"startTime":"2020-12-29T14:32:52.582-05:00[America/Bogota]","screenshots":[{"screenshot":"014f1f01c62fc569358026ed3b4edd8e30522c31fe52a7c1a519700608f4a605.png","timeStamp":1609270372582},{"screenshot":"36638b828d42275a17d3b1a560fa78ac7c4f1d81077e7be3d8acba6a2fb3f6dd.png","timeStamp":1609270373646}],"result":"SUCCESS","precondition":false,"level":2,"lineNumber":0},{"number":7,"description":"brandon enters \u0027Choucair2020*\u0027 into where do we write the password","duration":1881,"startTime":"2020-12-29T14:32:53.650-05:00[America/Bogota]","screenshots":[{"screenshot":"36638b828d42275a17d3b1a560fa78ac7c4f1d81077e7be3d8acba6a2fb3f6dd.png","timeStamp":1609270373666},{"screenshot":"b6510c4c9b5a5f7d6fb4987efe14dd93993a9f323d54b6e95f4339d9a9c4b27e.png","timeStamp":1609270375531}],"result":"SUCCESS","precondition":false,"level":2,"lineNumber":0},{"number":8,"description":"brandon clicks on button to confirm login","duration":3412,"startTime":"2020-12-29T14:32:55.537-05:00[America/Bogota]","screenshots":[{"screenshot":"b6510c4c9b5a5f7d6fb4987efe14dd93993a9f323d54b6e95f4339d9a9c4b27e.png","timeStamp":1609270375559},{"screenshot":"b4edb95ce427180a70791b474e0c4793c1c46fb618adb4a03398baad0bb7b6be.png","timeStamp":1609270378949}],"result":"SUCCESS","precondition":false,"level":2,"lineNumber":0}]}]},{"number":9,"description":"When he search for the course on the choucair academy platform\r\n| strCourse |\r\n| Prueba Técnica - Analista Bancolombia |","duration":11950,"startTime":"2020-12-29T14:32:58.986-05:00[America/Bogota]","screenshots":[{"screenshot":"1838603b27d21abf7b43349a6716a8dcabf4ead6de2cf6c5f6e056bb63cd56c9.png","timeStamp":1609270390936}],"result":"SUCCESS","precondition":false,"level":0,"lineNumber":0,"children":[{"number":10,"description":"Brandon search","duration":11414,"startTime":"2020-12-29T14:32:59.510-05:00[America/Bogota]","screenshots":[{"screenshot":"1838603b27d21abf7b43349a6716a8dcabf4ead6de2cf6c5f6e056bb63cd56c9.png","timeStamp":1609270390924}],"result":"SUCCESS","precondition":false,"level":1,"lineNumber":0,"children":[{"number":11,"description":"brandon clicks on selecciona cursos y calificaciones","duration":2909,"startTime":"2020-12-29T14:33:00.351-05:00[America/Bogota]","screenshots":[{"screenshot":"ff915e6bb63002c9a5afb0d3ebf30fddeeb74485536693001b4bc8045d10fe4a.png","timeStamp":1609270383260}],"result":"SUCCESS","precondition":false,"level":2,"lineNumber":0},{"number":12,"description":"brandon enters \u0027Prueba Técnica - Analista Bancolombia\u0027 into Buscar el curso","duration":1256,"startTime":"2020-12-29T14:33:03.268-05:00[America/Bogota]","screenshots":[{"screenshot":"ff915e6bb63002c9a5afb0d3ebf30fddeeb74485536693001b4bc8045d10fe4a.png","timeStamp":1609270383279},{"screenshot":"dbef9b7fd48b6d7da10f6adf3c6505e659549cf6d7218928d6571be14b495037.png","timeStamp":1609270384524}],"result":"SUCCESS","precondition":false,"level":2,"lineNumber":0},{"number":13,"description":"brandon clicks on Da click en IR para buscar el curso","duration":2471,"startTime":"2020-12-29T14:33:04.533-05:00[America/Bogota]","screenshots":[{"screenshot":"dbef9b7fd48b6d7da10f6adf3c6505e659549cf6d7218928d6571be14b495037.png","timeStamp":1609270384534},{"screenshot":"94208d4ef41c6c8e8bd37d1a1506bd92ca89b6fcd93e1ea3fab970f3173a5f2a.png","timeStamp":1609270387004}],"result":"SUCCESS","precondition":false,"level":2,"lineNumber":0},{"number":14,"description":"brandon clicks on Da click para buscar el curso","duration":3857,"startTime":"2020-12-29T14:33:07.054-05:00[America/Bogota]","screenshots":[{"screenshot":"499108f908f6505be091e31eecdad140057e2a2f0f272b3e06ddbe686b56e023.png","timeStamp":1609270387445},{"screenshot":"1838603b27d21abf7b43349a6716a8dcabf4ead6de2cf6c5f6e056bb63cd56c9.png","timeStamp":1609270390911}],"result":"SUCCESS","precondition":false,"level":2,"lineNumber":0}]}]},{"number":15,"description":"Then he finds the course called resources\r\n| strCourse |\r\n| Prueba Técnica - Analista Bancolombia |","duration":509,"startTime":"2020-12-29T14:33:10.943-05:00[America/Bogota]","screenshots":[{"screenshot":"1838603b27d21abf7b43349a6716a8dcabf4ead6de2cf6c5f6e056bb63cd56c9.png","htmlSource":"pagesource8472152220485611832.html.txt","timeStamp":1609270391452}],"exception":{"errorType":"cucumber.runtime.CucumberException","message":"Not a Map or List type: class java.lang.String","stackTrace":[{"declaringClass":"cucumber.runner.Runner","methodName":"runPickle","fileName":"Runner.java","lineNumber":80}]},"result":"ERROR","precondition":false,"level":0,"lineNumber":0}],"userStory":{"id":"academy-choucair","storyName":"Academy Choucair","path":"src/test/resources/features/academyChoucair.feature","narrative":"    As an user, I want to learn how to automate in screamplay at the Choucair Academy With the automation course","type":"feature"},"featureTag":{"name":"Features/Academy Choucair","type":"feature","displayName":"Features/Academy Choucair"},"title":"Search for an automation course","tags":[{"name":"scenario1","type":"tag","displayName":"scenario1"},{"name":"Academy Choucair","type":"feature","displayName":"Academy Choucair"},{"name":"stories","type":"tag","displayName":"stories"}],"startTime":"2020-12-29T14:32:39.534-05:00[America/Bogota]","duration":31918,"testFailureCause":{"errorType":"cucumber.runtime.CucumberException","message":"Not a Map or List type: class java.lang.String","stackTrace":[{"declaringClass":"cucumber.runner.Runner","methodName":"runPickle","fileName":"Runner.java","lineNumber":80}]},"testFailureClassname":"cucumber.runtime.CucumberException","testFailureMessage":"Not a Map or List type: class java.lang.String","testFailureSummary":"ERROR;cucumber.runtime.CucumberException;Not a Map or List type: class java.lang.String;Runner.java","projectKey":"","annotatedResult":"ERROR","sessionId":"5bd2b93a9ccb71ffae4fa47af7cb64fb","driver":"chrome:brandon","isManualTestingUpToDate":false,"manual":false,"testSource":"Cucumber","actors":[{"name":"brandon","can":["browse the web"]}],"result":"ERROR"}